README.md
bombchu.py
setup.py
bombchu.egg-info/PKG-INFO
bombchu.egg-info/SOURCES.txt
bombchu.egg-info/dependency_links.txt
bombchu.egg-info/entry_points.txt
bombchu.egg-info/requires.txt
bombchu.egg-info/top_level.txt