Metadata-Version: 2.1
Name: bombchu
Version: 0.1.3
Summary: Simple data manipulation tool with a bang.
Home-page: https://github.com/vesche/bombchu
Author: Austin Jackson
Author-email: vesche@protonmail.com
License: Unlicense
Platform: UNKNOWN
Classifier: Development Status :: 4 - Beta
Classifier: License :: Public Domain
Classifier: Programming Language :: Python :: 3
